parse_hh_data/__init__.py
parse_hh_data/download.py
parse_hh_data/parse.py
parse_hh_data-0.1.12.data/scripts/download
parse_hh_data-0.1.12.data/scripts/parse
parse_hh_data-0.1.12.dist-info/LICENSE
parse_hh_data-0.1.12.dist-info/METADATA
parse_hh_data-0.1.12.dist-info/WHEEL
parse_hh_data-0.1.12.dist-info/top_level.txt
parse_hh_data-0.1.12.dist-info/RECORD
