Metadata-Version: 2.1
Name: parse-hh-data
Version: 0.1.12
Summary: Package for parsing data (vacancies and resumes) from site hh.ru
Home-page: https://github.com/arinaaageeva/parse_hh_data
Author: Arina Ageeva
Author-email: arina.a.ageeva@gmail.com
License: UNKNOWN
Platform: UNKNOWN
Classifier: Programming Language :: Python :: 3
Classifier: License :: OSI Approved :: MIT License
Classifier: Operating System :: OS Independent
Requires-Python: >=3.6
Requires-Dist: beautifulsoup4 (==4.8.2)
Requires-Dist: random-user-agent (==1.0.1)
Requires-Dist: requests (==2.23.0)
Requires-Dist: tqdm (==4.44.1)
Requires-Dist: urllib3 (==1.25.8)
